src/__init__.py
unittest_CI-0.0.0.dist-info/METADATA
unittest_CI-0.0.0.dist-info/WHEEL
unittest_CI-0.0.0.dist-info/top_level.txt
unittest_CI-0.0.0.dist-info/RECORD
